open_cursor/__init__.py
open_cursor/agent_swarm.py
open_cursor/main.py
open_cursor/prompts.py
open_cursor_agent-0.1.0.dist-info/LICENSE
open_cursor_agent-0.1.0.dist-info/METADATA
open_cursor_agent-0.1.0.dist-info/WHEEL
open_cursor_agent-0.1.0.dist-info/RECORD
