Metadata-Version: 2.3
Name: open-cursor-agent
Version: 0.1.0
Summary: Swarms - TGSC
License: MIT
Keywords: artificial intelligence,deep learning,optimizers,Prompt Engineering,swarms,agents,llms,transformers,multi-agent,swarms of agents,Enterprise-Grade Agents,Production-Grade Agents,Agents,Multi-Grade-Agents,Swarms,Transformers,LLMs,Prompt Engineering,Agents,Generative Agents,Generative AI,Agent Marketplace,Agent Store,quant,finance,algorithmic trading,portfolio optimization,risk management,financial modeling,machine learning for finance,natural language processing for finance
Author: Kye Gomez
Author-email: kye@swarms.world
Requires-Python: >=3.10,<4.0
Classifier: Development Status :: 4 - Beta
Classifier: Intended Audience :: Developers
Classifier: License :: OSI Approved :: MIT License
Classifier: Programming Language :: Python :: 3
Classifier: Programming Language :: Python :: 3.10
Classifier: Programming Language :: Python :: 3.11
Classifier: Programming Language :: Python :: 3.12
Classifier: Programming Language :: Python :: 3.13
Classifier: Topic :: Scientific/Engineering :: Artificial Intelligence
Requires-Dist: loguru
Requires-Dist: python-dotenv
Requires-Dist: swarms
Requires-Dist: swarms-tools
Project-URL: Documentation, https://docs.swarms.world
Project-URL: Homepage, https://github.com/kyegomez/Open-Cursor-Agent
Project-URL: Repository, https://github.com/kyegomez/Open-Cursor-Agent
